cloudtipsadp/__init__.py
cloudtipsadp/api.py
cloudtipsadp/constants.py
cloudtipsadp/containers.py
cloudtipsadp/settings.py
cloudtipsadp/accumulations/__init__.py
cloudtipsadp/accumulations/services.py
cloudtipsadp/accumulations/connect/__init__.py
cloudtipsadp/accumulations/connect/repository.py
cloudtipsadp/accumulations/connect/spec.py
cloudtipsadp/cards/__init__.py
cloudtipsadp/cards/services.py
cloudtipsadp/cards/connect/__init__.py
cloudtipsadp/cards/connect/models.py
cloudtipsadp/cards/connect/repository.py
cloudtipsadp/cards/connect/spec.py
cloudtipsadp/connect/__init__.py
cloudtipsadp/connect/clients.py
cloudtipsadp/connect/exceptions.py
cloudtipsadp/connect/repository.py
cloudtipsadp/connect/sessions.py
cloudtipsadp/connect/spec.py
cloudtipsadp/connect/unit_of_work.py
cloudtipsadp/payouts/__init__.py
cloudtipsadp/payouts/services.py
cloudtipsadp/payouts/connect/__init__.py
cloudtipsadp/payouts/connect/repository.py
cloudtipsadp/payouts/connect/spec.py
cloudtipsadp/places/__init__.py
cloudtipsadp/places/services.py
cloudtipsadp/places/connect/__init__.py
cloudtipsadp/places/connect/repository.py
cloudtipsadp/places/connect/spec.py
cloudtipsadp/receivers/__init__.py
cloudtipsadp/receivers/services.py
cloudtipsadp/receivers/connect/__init__.py
cloudtipsadp/receivers/connect/models.py
cloudtipsadp/receivers/connect/repository.py
cloudtipsadp/receivers/connect/spec.py
cloudtipsadp-0.15.2.dist-info/METADATA
cloudtipsadp-0.15.2.dist-info/WHEEL
cloudtipsadp-0.15.2.dist-info/licenses/LICENSE
cloudtipsadp-0.15.2.dist-info/RECORD
