Metadata-Version: 2.1
Name: cloudtipsadp
Version: 0.15.2
Summary: CloudTips Adapter - integration module with API CloudPayments.
Project-URL: Homepage, https://github.com/SETTER2000/cloudtips-adp
Project-URL: Bug Tracker, https://github.com/SETTER2000/cloudtips-adp/issues
Author-email: setter <lphp@mail.ru>
License: MIT License
Classifier: License :: OSI Approved :: MIT License
Classifier: Operating System :: OS Independent
Classifier: Programming Language :: Python :: 3
Requires-Python: >=3.9
